bedsheet/__init__.py
bedsheet/__main__.py
bedsheet/action_group.py
bedsheet/agent.py
bedsheet/events.py
bedsheet/exceptions.py
bedsheet/supervisor.py
bedsheet/testing.py
bedsheet/cli/README.md
bedsheet/cli/__init__.py
bedsheet/cli/main.py
bedsheet/deploy/README.md
bedsheet/deploy/__init__.py
bedsheet/deploy/config.py
bedsheet/deploy/introspect.py
bedsheet/deploy/targets/__init__.py
bedsheet/deploy/targets/aws.py
bedsheet/deploy/targets/aws_terraform.py
bedsheet/deploy/targets/base.py
bedsheet/deploy/targets/gcp.py
bedsheet/deploy/targets/local.py
bedsheet/deploy/templates/__init__.py
bedsheet/deploy/templates/aws/Makefile.j2
bedsheet/deploy/templates/aws/__init__.py
bedsheet/deploy/templates/aws/cdk_app.py.j2
bedsheet/deploy/templates/aws/cdk_json.j2
bedsheet/deploy/templates/aws/cdk_stack.py.j2
bedsheet/deploy/templates/aws/env.example.j2
bedsheet/deploy/templates/aws/github_workflows_ci.yaml.j2
bedsheet/deploy/templates/aws/github_workflows_deploy.yaml.j2
bedsheet/deploy/templates/aws/lambda_handler.py.j2
bedsheet/deploy/templates/aws/lambda_requirements.txt.j2
bedsheet/deploy/templates/aws/openapi.yaml.j2
bedsheet/deploy/templates/aws/pyproject.toml.j2
bedsheet/deploy/templates/aws/stacks_init.py.j2
bedsheet/deploy/templates/aws/debug-ui/server.py.j2
bedsheet/deploy/templates/aws-terraform/Makefile.j2
bedsheet/deploy/templates/aws-terraform/env.example.j2
bedsheet/deploy/templates/aws-terraform/github_workflows_ci.yaml.j2
bedsheet/deploy/templates/aws-terraform/github_workflows_deploy.yaml.j2
bedsheet/deploy/templates/aws-terraform/lambda_handler.py.j2
bedsheet/deploy/templates/aws-terraform/lambda_requirements.txt.j2
bedsheet/deploy/templates/aws-terraform/main.tf.j2
bedsheet/deploy/templates/aws-terraform/openapi.yaml.j2
bedsheet/deploy/templates/aws-terraform/outputs.tf.j2
bedsheet/deploy/templates/aws-terraform/pyproject.toml.j2
bedsheet/deploy/templates/aws-terraform/terraform.tfvars.example.j2
bedsheet/deploy/templates/aws-terraform/variables.tf.j2
bedsheet_agents-0.4.0.dist-info/METADATA
bedsheet_agents-0.4.0.dist-info/WHEEL
bedsheet_agents-0.4.0.dist-info/entry_points.txt
bedsheet_agents-0.4.0.dist-info/licenses/LICENSE.md
bedsheet_agents-0.4.0.dist-info/RECORD
