Metadata-Version: 2.4
Name: bedsheet-agents
Version: 0.4.0
Summary: Pythonic framework for AI agents. Build single agents or multi-agent teams with streaming events, parallel execution, and full observability.
Project-URL: Homepage, https://github.com/sivang/bedsheet
Project-URL: Documentation, https://github.com/sivang/bedsheet#readme
Project-URL: Repository, https://github.com/sivang/bedsheet
Project-URL: Issues, https://github.com/sivang/bedsheet/issues
Author-email: Sivan Grunberg <sivan@vitakka.co>
License: Elastic License 2.0
License-File: LICENSE.md
Keywords: agents,ai,anthropic,bedrock,claude,llm,multi-agent,orchestration
Classifier: Development Status :: 4 - Beta
Classifier: Intended Audience :: Developers
Classifier: License :: Other/Proprietary License
Classifier: Programming Language :: Python :: 3
Classifier: Programming Language :: Python :: 3.11
Classifier: Programming Language :: Python :: 3.12
Classifier: Topic :: Scientific/Engineering :: Artificial Intelligence
Classifier: Topic :: Software Development :: Libraries :: Python Modules
Classifier: Typing :: Typed
Requires-Python: >=3.11
Requires-Dist: anthropic>=0.39.0
Requires-Dist: jinja2>=3.1.0
Requires-Dist: pydantic>=2.0.0
Requires-Dist: pyyaml>=6.0.0
Requires-Dist: rich>=13.0.0
Requires-Dist: typer>=0.9.0
Provides-Extra: aws
Requires-Dist: jinja2>=3.1.0; extra == 'aws'
Requires-Dist: pydantic>=2.0.0; extra == 'aws'
Requires-Dist: pyyaml>=6.0.0; extra == 'aws'
Requires-Dist: typer>=0.9.0; extra == 'aws'
Provides-Extra: deploy
Requires-Dist: jinja2>=3.1.0; extra == 'deploy'
Requires-Dist: pydantic>=2.0.0; extra == 'deploy'
Requires-Dist: pyyaml>=6.0.0; extra == 'deploy'
Requires-Dist: typer>=0.9.0; extra == 'deploy'
Provides-Extra: dev
Requires-Dist: jinja2>=3.1.0; extra == 'dev'
Requires-Dist: pydantic>=2.0.0; extra == 'dev'
Requires-Dist: pytest-asyncio>=0.24.0; extra == 'dev'
Requires-Dist: pytest>=8.0.0; extra == 'dev'
Requires-Dist: pyyaml>=6.0.0; extra == 'dev'
Requires-Dist: redis>=5.0.0; extra == 'dev'
Requires-Dist: typer>=0.9.0; extra == 'dev'
Provides-Extra: gcp
Requires-Dist: jinja2>=3.1.0; extra == 'gcp'
Requires-Dist: pydantic>=2.0.0; extra == 'gcp'
Requires-Dist: pyyaml>=6.0.0; extra == 'gcp'
Requires-Dist: typer>=0.9.0; extra == 'gcp'
Provides-Extra: redis
Requires-Dist: redis>=5.0.0; extra == 'redis'
